LICENSE
README.md
setup.py
exotedrf/__init__.py
exotedrf/extra_functions.py
exotedrf/fit_lightcurves.py
exotedrf/plotting.py
exotedrf/run_DMS.py
exotedrf/stage1.py
exotedrf/stage2.py
exotedrf/stage3.py
exotedrf/stage4.py
exotedrf/utils.py
exotedrf.egg-info/PKG-INFO
exotedrf.egg-info/SOURCES.txt
exotedrf.egg-info/dependency_links.txt
exotedrf.egg-info/requires.txt
exotedrf.egg-info/top_level.txt