Metadata-Version: 2.1
Name: exotedrf
Version: 2.4.0
Summary: Tools for Reduction of JWST TSOs
Home-page: https://github.com/radicamc/exoTEDRF
Author: Michael Radica
Author-email: radicamc@uchicago.edu
License: MIT
Classifier: Development Status :: 3 - Alpha
Classifier: Intended Audience :: Science/Research
Classifier: License :: OSI Approved :: MIT License
Classifier: Operating System :: OS Independent
Classifier: Programming Language :: Python :: 3.10
License-File: LICENSE
Requires-Dist: applesoss==2.1.0
Requires-Dist: astropy
Requires-Dist: astroquery
Requires-Dist: bottleneck
Requires-Dist: crds==12.1.11
Requires-Dist: corner
Requires-Dist: jwst==1.17.1
Requires-Dist: matplotlib
Requires-Dist: more_itertools
Requires-Dist: numpy==1.24.4
Requires-Dist: pandas
Requires-Dist: ray
Requires-Dist: scikit-learn
Requires-Dist: scipy
Requires-Dist: spectres
Requires-Dist: requests
Requires-Dist: tqdm
Requires-Dist: pastasoss
Requires-Dist: pyyaml
Provides-Extra: stage4
Requires-Dist: exotedrf; extra == "stage4"
Requires-Dist: exouprf==1.1.0; extra == "stage4"
Requires-Dist: exotic_ld; extra == "stage4"
Requires-Dist: h5py; extra == "stage4"
Provides-Extra: webbpsf
Requires-Dist: exotedrf; extra == "webbpsf"
Requires-Dist: webbpsf>=1.1.1; extra == "webbpsf"
